hexaboost/__init__.py
hexaboost/cli/__init__.py
hexaboost/cli/main.py
hexaboost/cli/test_init_cmd.py
hexaboost/cli/test_new_cmd.py
hexaboost/cli/test_sync_readme_cmd.py
hexaboost/cli/utils.py
hexaboost/cli/commands/__init__.py
hexaboost/cli/commands/init.py
hexaboost/cli/commands/init_cmd.py
hexaboost/cli/commands/new.py
hexaboost/cli/commands/new_cmd.py
hexaboost/cli/commands/sync_readme.py
hexaboost/cli/commands/sync_readme_cmd.py
hexaboost/cli/myproject2/app/main.py
hexaboost/scripts/sync_readme.py
hexaboost/tests/cli/test_sync_readme.py
hexaboost/utils/__init__.py
hexaboost/utils/file_ops.py
hexaboost/utils/logger.py
hexaboost/utils/validators.py
hexaboost-1.0.1.dist-info/licenses/LICENSE
hexaboost-1.0.1.dist-info/METADATA
hexaboost-1.0.1.dist-info/WHEEL
hexaboost-1.0.1.dist-info/entry_points.txt
hexaboost-1.0.1.dist-info/top_level.txt
hexaboost-1.0.1.dist-info/RECORD
