Metadata-Version: 2.4
Name: hexaboost
Version: 1.0.1
Summary: Hexaboost - CLI para generar proyectos en Python con plantillas listas
License-Expression: MIT
Project-URL: Homepage, https://github.com/tu-usuario/hexaboost
Project-URL: Repository, https://github.com/tu-usuario/hexaboost
Project-URL: Issues, https://github.com/tu-usuario/hexaboost/issues
Keywords: cli,scaffolding,python,boost,templates
Classifier: Development Status :: 5 - Production/Stable
Classifier: Programming Language :: Python :: 3
Classifier: Programming Language :: Python :: 3.8
Classifier: Programming Language :: Python :: 3.9
Classifier: Programming Language :: Python :: 3.10
Classifier: Programming Language :: Python :: 3.11
Classifier: Programming Language :: Python :: 3.12
Classifier: Operating System :: OS Independent
Requires-Python: >=3.8
License-File: LICENSE
Requires-Dist: click>=8.0
Dynamic: license-file
